petnames/__init__.py
petnames/petnames.py
petnames/version.py
petnames-0.2.20251202.dist-info/METADATA
petnames-0.2.20251202.dist-info/WHEEL
petnames-0.2.20251202.dist-info/entry_points.txt
petnames-0.2.20251202.dist-info/licenses/COPYING
petnames-0.2.20251202.dist-info/licenses/LICENCE
petnames-0.2.20251202.dist-info/RECORD
