Metadata-Version: 2.4
Name: petnames
Version: 0.2.20251202
Summary: PetName and Distributed Directory Name resolver
Project-URL: source, https://codeberg.org/skyguy/petnames
Author-email: Kevin Steen <code@kevinsteen.net>
License-Expression: AGPL-3.0-or-later
License-File: COPYING
License-File: LICENCE
Keywords: ddig,dig,dns,i2p,mesh,p2p,yggdrasil
Classifier: Development Status :: 4 - Beta
Classifier: Intended Audience :: Developers
Classifier: License :: OSI Approved :: GNU Affero General Public License v3 or later (AGPLv3+)
Classifier: Operating System :: OS Independent
Classifier: Programming Language :: Python :: 3 :: Only
Classifier: Topic :: Communications
Requires-Python: >=3.12
Provides-Extra: dev
Requires-Dist: pytest; extra == 'dev'
